{
 "panel": [
  {
   "surface": "끱뀁뷔끶뀢죠달리",
   "swap_target": "끶뀢뷔끱뀁죠달리",
   "cell": {
    "class_subj": 0,
    "marker": 0,
    "order": "SOV",
    "gold": 0,
    "n_subj": "끱뀁",
    "n_obj": "끶뀢"
   },
   "answered": true,
   "gold_token": "네"
  },
  {
   "surface": "끳뀃뷔꾙뀥죠달리",
   "swap_target": "꾙뀥뷔끳뀃죠달리",
   "cell": {
    "class_subj": 0,
    "marker": 0,
    "order": "SOV",
    "gold": 0,
    "n_subj": "끳뀃",
    "n_obj": "꾙뀥"
   },
   "answered": true,
   "gold_token": "네"
  },
  {
   "surface": "끹뀉뷔끳뀟죠달리",
   "swap_target": "끳뀟뷔끹뀉죠달리",
   "cell": {
    "class_subj": 0,
    "marker": 0,
    "order": "SOV",
    "gold": 0,
    "n_subj": "끹뀉",
    "n_obj": "끳뀟"
   },
   "answered": true,
   "gold_token": "네"
  },
  {
   "surface": "끶뀆뷔꾑뀝죠달리",
   "swap_target": "꾑뀝뷔끶뀆죠달리",
   "cell": {
    "class_subj": 0,
    "marker": 0,
    "order": "SOV",
    "gold": 0,
    "n_subj": "끶뀆",
    "n_obj": "꾑뀝"
   },
   "answered": true,
   "gold_token": "네"
  },
  {
   "surface": "끩꿹뷔꾍꿽죠달리",
   "swap_target": "꾍꿽뷔끩꿹죠달리",
   "cell": {
    "class_subj": 0,
    "marker": 0,
    "order": "SOV",
    "gold": 0,
    "n_subj": "끩꿹",
    "n_obj": "꾍꿽"
   },
   "answered": true,
   "gold_token": "네"
  },
  {
   "surface": "끭꿽뷔끩꿹죠달리",
   "swap_target": "끩꿹뷔끭꿽죠달리",
   "cell": {
    "class_subj": 0,
    "marker": 0,
    "order": "SOV",
    "gold": 0,
    "n_subj": "끭꿽",
    "n_obj": "끩꿹"
   },
   "answered": true,
   "gold_token": "네"
  },
  {
   "surface": "꾑뀝뷔꾖뀆죠달리",
   "swap_target": "꾖뀆뷔꾑뀝죠달리",
   "cell": {
    "class_subj": 0,
    "marker": 0,
    "order": "SOV",
    "gold": 0,
    "n_subj": "꾑뀝",
    "n_obj": "꾖뀆"
   },
   "answered": true,
   "gold_token": "네"
  },
  {
   "surface": "꾓뀟뷔끹뀉죠달리",
   "swap_target": "끹뀉뷔꾓뀟죠달리",
   "cell": {
    "class_subj": 0,
    "marker": 0,
    "order": "SOV",
    "gold": 0,
    "n_subj": "꾓뀟",
    "n_obj": "끹뀉"
   },
   "answered": true,
   "gold_token": "네"
  },
  {
   "surface": "꾙뀥뷔꾓뀃죠달리",
   "swap_target": "꾓뀃뷔꾙뀥죠달리",
   "cell": {
    "class_subj": 0,
    "marker": 0,
    "order": "SOV",
    "gold": 0,
    "n_subj": "꾙뀥",
    "n_obj": "꾓뀃"
   },
   "answered": true,
   "gold_token": "네"
  },
  {
   "surface": "꾖뀢뷔끱뀁죠달리",
   "swap_target": "끱뀁뷔꾖뀢죠달리",
   "cell": {
    "class_subj": 0,
    "marker": 0,
    "order": "SOV",
    "gold": 0,
    "n_subj": "꾖뀢",
    "n_obj": "끱뀁"
   },
   "answered": true,
   "gold_token": "네"
  },
  {
   "surface": "꾉뀕뷔끭뀙죠달리",
   "swap_target": "끭뀙뷔꾉뀕죠달리",
   "cell": {
    "class_subj": 0,
    "marker": 0,
    "order": "SOV",
    "gold": 0,
    "n_subj": "꾉뀕",
    "n_obj": "끭뀙"
   },
   "answered": true,
   "gold_token": "네"
  },
  {
   "surface": "꾍뀙뷔꾉뀕죠달리",
   "swap_target": "꾉뀕뷔꾍뀙죠달리",
   "cell": {
    "class_subj": 0,
    "marker": 0,
    "order": "SOV",
    "gold": 0,
    "n_subj": "꾍뀙",
    "n_obj": "꾉뀕"
   },
   "answered": true,
   "gold_token": "네"
  },
  {
   "surface": "끱뀁뷔끩뀕죠달리",
   "swap_target": "끩뀕뷔끱뀁죠달리",
   "cell": {
    "class_subj": 0,
    "marker": 0,
    "order": "SOV",
    "gold": 0,
    "n_subj": "끱뀁",
    "n_obj": "끩뀕"
   },
   "answered": true,
   "gold_token": "네"
  },
  {
   "surface": "끳뀃뷔꾖뀢죠달리",
   "swap_target": "꾖뀢뷔끳뀃죠달리",
   "cell": {
    "class_subj": 0,
    "marker": 0,
    "order": "SOV",
    "gold": 0,
    "n_subj": "끳뀃",
    "n_obj": "꾖뀢"
   },
   "answered": true,
   "gold_token": "네"
  },
  {
   "surface": "끹뀉뷔끹뀥죠달리",
   "swap_target": "끹뀥뷔끹뀉죠달리",
   "cell": {
    "class_subj": 0,
    "marker": 0,
    "order": "SOV",
    "gold": 0,
    "n_subj": "끹뀉",
    "n_obj": "끹뀥"
   },
   "answered": true,
   "gold_token": "네"
  },
  {
   "surface": "끶뀆뷔꾓뀟죠달리",
   "swap_target": "꾓뀟뷔끶뀆죠달리",
   "cell": {
    "class_subj": 0,
    "marker": 0,
    "order": "SOV",
    "gold": 0,
    "n_subj": "끶뀆",
    "n_obj": "꾓뀟"
   },
   "answered": true,
   "gold_token": "네"
  },
  {
   "surface": "끩꿹뷔끱뀝죠달리",
   "swap_target": "끱뀝뷔끩꿹죠달리",
   "cell": {
    "class_subj": 0,
    "marker": 0,
    "order": "SOV",
    "gold": 0,
    "n_subj": "끩꿹",
    "n_obj": "끱뀝"
   },
   "answered": true,
   "gold_token": "네"
  },
  {
   "surface": "꾑뀝뷔꾉뀕죠달리",
   "swap_target": "꾉뀕뷔꾑뀝죠달리",
   "cell": {
    "class_subj": 0,
    "marker": 0,
    "order": "SOV",
    "gold": 0,
    "n_subj": "꾑뀝",
    "n_obj": "꾉뀕"
   },
   "answered": true,
   "gold_token": "네"
  },
  {
   "surface": "꾓뀟뷔끶뀢죠달리",
   "swap_target": "끶뀢뷔꾓뀟죠달리",
   "cell": {
    "class_subj": 0,
    "marker": 0,
    "order": "SOV",
    "gold": 0,
    "n_subj": "꾓뀟",
    "n_obj": "끶뀢"
   },
   "answered": true,
   "gold_token": "네"
  },
  {
   "surface": "꾖뀢뷔끳뀃죠달리",
   "swap_target": "끳뀃뷔꾖뀢죠달리",
   "cell": {
    "class_subj": 0,
    "marker": 0,
    "order": "SOV",
    "gold": 0,
    "n_subj": "꾖뀢",
    "n_obj": "끳뀃"
   },
   "answered": true,
   "gold_token": "네"
  },
  {
   "surface": "꾉뀕뷔꾑뀁죠달리",
   "swap_target": "꾑뀁뷔꾉뀕죠달리",
   "cell": {
    "class_subj": 0,
    "marker": 0,
    "order": "SOV",
    "gold": 0,
    "n_subj": "꾉뀕",
    "n_obj": "꾑뀁"
   },
   "answered": true,
   "gold_token": "네"
  },
  {
   "surface": "끱뀁뷔끭꿽죠달리",
   "swap_target": "끭꿽뷔끱뀁죠달리",
   "cell": {
    "class_subj": 0,
    "marker": 0,
    "order": "SOV",
    "gold": 0,
    "n_subj": "끱뀁",
    "n_obj": "끭꿽"
   },
   "answered": true,
   "gold_token": "네"
  },
  {
   "surface": "끳뀃뷔꾉꿹죠달리",
   "swap_target": "꾉꿹뷔끳뀃죠달리",
   "cell": {
    "class_subj": 0,
    "marker": 0,
    "order": "SOV",
    "gold": 0,
    "n_subj": "끳뀃",
    "n_obj": "꾉꿹"
   },
   "answered": true,
   "gold_token": "네"
  },
  {
   "surface": "끶뀆뷔꾙뀥죠달리",
   "swap_target": "꾙뀥뷔끶뀆죠달리",
   "cell": {
    "class_subj": 0,
    "marker": 0,
    "order": "SOV",
    "gold": 0,
    "n_subj": "끶뀆",
    "n_obj": "꾙뀥"
   },
   "answered": true,
   "gold_token": "네"
  },
  {
   "surface": "끶뀢죠끱뀁뷔달리",
   "swap_target": "끱뀁죠끶뀢뷔달리",
   "cell": {
    "class_subj": 0,
    "marker": 0,
    "order": "OSV",
    "gold": 0,
    "n_subj": "끱뀁",
    "n_obj": "끶뀢"
   },
   "answered": true,
   "gold_token": "네"
  },
  {
   "surface": "꾙뀥죠끳뀃뷔달리",
   "swap_target": "끳뀃죠꾙뀥뷔달리",
   "cell": {
    "class_subj": 0,
    "marker": 0,
    "order": "OSV",
    "gold": 0,
    "n_subj": "끳뀃",
    "n_obj": "꾙뀥"
   },
   "answered": true,
   "gold_token": "네"
  },
  {
   "surface": "끳뀟죠끹뀉뷔달리",
   "swap_target": "끹뀉죠끳뀟뷔달리",
   "cell": {
    "class_subj": 0,
    "marker": 0,
    "order": "OSV",
    "gold": 0,
    "n_subj": "끹뀉",
    "n_obj": "끳뀟"
   },
   "answered": true,
   "gold_token": "네"
  },
  {
   "surface": "꾑뀝죠끶뀆뷔달리",
   "swap_target": "끶뀆죠꾑뀝뷔달리",
   "cell": {
    "class_subj": 0,
    "marker": 0,
    "order": "OSV",
    "gold": 0,
    "n_subj": "끶뀆",
    "n_obj": "꾑뀝"
   },
   "answered": true,
   "gold_token": "네"
  },
  {
   "surface": "꾍꿽죠끩꿹뷔달리",
   "swap_target": "끩꿹죠꾍꿽뷔달리",
   "cell": {
    "class_subj": 0,
    "marker": 0,
    "order": "OSV",
    "gold": 0,
    "n_subj": "끩꿹",
    "n_obj": "꾍꿽"
   },
   "answered": true,
   "gold_token": "네"
  },
  {
   "surface": "끩꿹죠끭꿽뷔달리",
   "swap_target": "끭꿽죠끩꿹뷔달리",
   "cell": {
    "class_subj": 0,
    "marker": 0,
    "order": "OSV",
    "gold": 0,
    "n_subj": "끭꿽",
    "n_obj": "끩꿹"
   },
   "answered": true,
   "gold_token": "네"
  },
  {
   "surface": "꾖뀆죠꾑뀝뷔달리",
   "swap_target": "꾑뀝죠꾖뀆뷔달리",
   "cell": {
    "class_subj": 0,
    "marker": 0,
    "order": "OSV",
    "gold": 0,
    "n_subj": "꾑뀝",
    "n_obj": "꾖뀆"
   },
   "answered": true,
   "gold_token": "네"
  },
  {
   "surface": "끹뀉죠꾓뀟뷔달리",
   "swap_target": "꾓뀟죠끹뀉뷔달리",
   "cell": {
    "class_subj": 0,
    "marker": 0,
    "order": "OSV",
    "gold": 0,
    "n_subj": "꾓뀟",
    "n_obj": "끹뀉"
   },
   "answered": true,
   "gold_token": "네"
  },
  {
   "surface": "꾓뀃죠꾙뀥뷔달리",
   "swap_target": "꾙뀥죠꾓뀃뷔달리",
   "cell": {
    "class_subj": 0,
    "marker": 0,
    "order": "OSV",
    "gold": 0,
    "n_subj": "꾙뀥",
    "n_obj": "꾓뀃"
   },
   "answered": true,
   "gold_token": "네"
  },
  {
   "surface": "끱뀁죠꾖뀢뷔달리",
   "swap_target": "꾖뀢죠끱뀁뷔달리",
   "cell": {
    "class_subj": 0,
    "marker": 0,
    "order": "OSV",
    "gold": 0,
    "n_subj": "꾖뀢",
    "n_obj": "끱뀁"
   },
   "answered": true,
   "gold_token": "네"
  },
  {
   "surface": "끭뀙죠꾉뀕뷔달리",
   "swap_target": "꾉뀕죠끭뀙뷔달리",
   "cell": {
    "class_subj": 0,
    "marker": 0,
    "order": "OSV",
    "gold": 0,
    "n_subj": "꾉뀕",
    "n_obj": "끭뀙"
   },
   "answered": true,
   "gold_token": "네"
  },
  {
   "surface": "꾉뀕죠꾍뀙뷔달리",
   "swap_target": "꾍뀙죠꾉뀕뷔달리",
   "cell": {
    "class_subj": 0,
    "marker": 0,
    "order": "OSV",
    "gold": 0,
    "n_subj": "꾍뀙",
    "n_obj": "꾉뀕"
   },
   "answered": true,
   "gold_token": "네"
  },
  {
   "surface": "끩뀕죠끱뀁뷔달리",
   "swap_target": "끱뀁죠끩뀕뷔달리",
   "cell": {
    "class_subj": 0,
    "marker": 0,
    "order": "OSV",
    "gold": 0,
    "n_subj": "끱뀁",
    "n_obj": "끩뀕"
   },
   "answered": true,
   "gold_token": "네"
  },
  {
   "surface": "꾖뀢죠끳뀃뷔달리",
   "swap_target": "끳뀃죠꾖뀢뷔달리",
   "cell": {
    "class_subj": 0,
    "marker": 0,
    "order": "OSV",
    "gold": 0,
    "n_subj": "끳뀃",
    "n_obj": "꾖뀢"
   },
   "answered": true,
   "gold_token": "네"
  },
  {
   "surface": "끹뀥죠끹뀉뷔달리",
   "swap_target": "끹뀉죠끹뀥뷔달리",
   "cell": {
    "class_subj": 0,
    "marker": 0,
    "order": "OSV",
    "gold": 0,
    "n_subj": "끹뀉",
    "n_obj": "끹뀥"
   },
   "answered": true,
   "gold_token": "네"
  },
  {
   "surface": "꾓뀟죠끶뀆뷔달리",
   "swap_target": "끶뀆죠꾓뀟뷔달리",
   "cell": {
    "class_subj": 0,
    "marker": 0,
    "order": "OSV",
    "gold": 0,
    "n_subj": "끶뀆",
    "n_obj": "꾓뀟"
   },
   "answered": true,
   "gold_token": "네"
  },
  {
   "surface": "끱뀝죠끩꿹뷔달리",
   "swap_target": "끩꿹죠끱뀝뷔달리",
   "cell": {
    "class_subj": 0,
    "marker": 0,
    "order": "OSV",
    "gold": 0,
    "n_subj": "끩꿹",
    "n_obj": "끱뀝"
   },
   "answered": true,
   "gold_token": "네"
  },
  {
   "surface": "꾉뀕죠꾑뀝뷔달리",
   "swap_target": "꾑뀝죠꾉뀕뷔달리",
   "cell": {
    "class_subj": 0,
    "marker": 0,
    "order": "OSV",
    "gold": 0,
    "n_subj": "꾑뀝",
    "n_obj": "꾉뀕"
   },
   "answered": true,
   "gold_token": "네"
  },
  {
   "surface": "끶뀢죠꾓뀟뷔달리",
   "swap_target": "꾓뀟죠끶뀢뷔달리",
   "cell": {
    "class_subj": 0,
    "marker": 0,
    "order": "OSV",
    "gold": 0,
    "n_subj": "꾓뀟",
    "n_obj": "끶뀢"
   },
   "answered": true,
   "gold_token": "네"
  },
  {
   "surface": "끳뀃죠꾖뀢뷔달리",
   "swap_target": "꾖뀢죠끳뀃뷔달리",
   "cell": {
    "class_subj": 0,
    "marker": 0,
    "order": "OSV",
    "gold": 0,
    "n_subj": "꾖뀢",
    "n_obj": "끳뀃"
   },
   "answered": true,
   "gold_token": "네"
  },
  {
   "surface": "꾑뀁죠꾉뀕뷔달리",
   "swap_target": "꾉뀕죠꾑뀁뷔달리",
   "cell": {
    "class_subj": 0,
    "marker": 0,
    "order": "OSV",
    "gold": 0,
    "n_subj": "꾉뀕",
    "n_obj": "꾑뀁"
   },
   "answered": true,
   "gold_token": "네"
  },
  {
   "surface": "끭꿽죠끱뀁뷔달리",
   "swap_target": "끱뀁죠끭꿽뷔달리",
   "cell": {
    "class_subj": 0,
    "marker": 0,
    "order": "OSV",
    "gold": 0,
    "n_subj": "끱뀁",
    "n_obj": "끭꿽"
   },
   "answered": true,
   "gold_token": "네"
  },
  {
   "surface": "꾉꿹죠끳뀃뷔달리",
   "swap_target": "끳뀃죠꾉꿹뷔달리",
   "cell": {
    "class_subj": 0,
    "marker": 0,
    "order": "OSV",
    "gold": 0,
    "n_subj": "끳뀃",
    "n_obj": "꾉꿹"
   },
   "answered": true,
   "gold_token": "네"
  },
  {
   "surface": "꾙뀥죠끶뀆뷔달리",
   "swap_target": "끶뀆죠꾙뀥뷔달리",
   "cell": {
    "class_subj": 0,
    "marker": 0,
    "order": "OSV",
    "gold": 0,
    "n_subj": "끶뀆",
    "n_obj": "꾙뀥"
   },
   "answered": true,
   "gold_token": "네"
  },
  {
   "surface": "끱뀁뷔끶뀢퓨달리",
   "swap_target": "끶뀢뷔끱뀁퓨달리",
   "cell": {
    "class_subj": 0,
    "marker": 1,
    "order": "SOV",
    "gold": 1,
    "n_subj": "끱뀁",
    "n_obj": "끶뀢"
   },
   "answered": true,
   "gold_token": "지"
  },
  {
   "surface": "끳뀃뷔꾙뀥퓨달리",
   "swap_target": "꾙뀥뷔끳뀃퓨달리",
   "cell": {
    "class_subj": 0,
    "marker": 1,
    "order": "SOV",
    "gold": 1,
    "n_subj": "끳뀃",
    "n_obj": "꾙뀥"
   },
   "answered": true,
   "gold_token": "지"
  },
  {
   "surface": "끹뀉뷔끳뀟퓨달리",
   "swap_target": "끳뀟뷔끹뀉퓨달리",
   "cell": {
    "class_subj": 0,
    "marker": 1,
    "order": "SOV",
    "gold": 1,
    "n_subj": "끹뀉",
    "n_obj": "끳뀟"
   },
   "answered": true,
   "gold_token": "지"
  },
  {
   "surface": "끶뀆뷔꾑뀝퓨달리",
   "swap_target": "꾑뀝뷔끶뀆퓨달리",
   "cell": {
    "class_subj": 0,
    "marker": 1,
    "order": "SOV",
    "gold": 1,
    "n_subj": "끶뀆",
    "n_obj": "꾑뀝"
   },
   "answered": true,
   "gold_token": "지"
  },
  {
   "surface": "끩꿹뷔꾍꿽퓨달리",
   "swap_target": "꾍꿽뷔끩꿹퓨달리",
   "cell": {
    "class_subj": 0,
    "marker": 1,
    "order": "SOV",
    "gold": 1,
    "n_subj": "끩꿹",
    "n_obj": "꾍꿽"
   },
   "answered": true,
   "gold_token": "지"
  },
  {
   "surface": "끭꿽뷔끩꿹퓨달리",
   "swap_target": "끩꿹뷔끭꿽퓨달리",
   "cell": {
    "class_subj": 0,
    "marker": 1,
    "order": "SOV",
    "gold": 1,
    "n_subj": "끭꿽",
    "n_obj": "끩꿹"
   },
   "answered": true,
   "gold_token": "지"
  },
  {
   "surface": "꾑뀝뷔꾖뀆퓨달리",
   "swap_target": "꾖뀆뷔꾑뀝퓨달리",
   "cell": {
    "class_subj": 0,
    "marker": 1,
    "order": "SOV",
    "gold": 1,
    "n_subj": "꾑뀝",
    "n_obj": "꾖뀆"
   },
   "answered": true,
   "gold_token": "지"
  },
  {
   "surface": "꾓뀟뷔끹뀉퓨달리",
   "swap_target": "끹뀉뷔꾓뀟퓨달리",
   "cell": {
    "class_subj": 0,
    "marker": 1,
    "order": "SOV",
    "gold": 1,
    "n_subj": "꾓뀟",
    "n_obj": "끹뀉"
   },
   "answered": true,
   "gold_token": "지"
  },
  {
   "surface": "꾙뀥뷔꾓뀃퓨달리",
   "swap_target": "꾓뀃뷔꾙뀥퓨달리",
   "cell": {
    "class_subj": 0,
    "marker": 1,
    "order": "SOV",
    "gold": 1,
    "n_subj": "꾙뀥",
    "n_obj": "꾓뀃"
   },
   "answered": true,
   "gold_token": "지"
  },
  {
   "surface": "꾖뀢뷔끱뀁퓨달리",
   "swap_target": "끱뀁뷔꾖뀢퓨달리",
   "cell": {
    "class_subj": 0,
    "marker": 1,
    "order": "SOV",
    "gold": 1,
    "n_subj": "꾖뀢",
    "n_obj": "끱뀁"
   },
   "answered": true,
   "gold_token": "지"
  },
  {
   "surface": "꾉뀕뷔끭뀙퓨달리",
   "swap_target": "끭뀙뷔꾉뀕퓨달리",
   "cell": {
    "class_subj": 0,
    "marker": 1,
    "order": "SOV",
    "gold": 1,
    "n_subj": "꾉뀕",
    "n_obj": "끭뀙"
   },
   "answered": true,
   "gold_token": "지"
  },
  {
   "surface": "꾍뀙뷔꾉뀕퓨달리",
   "swap_target": "꾉뀕뷔꾍뀙퓨달리",
   "cell": {
    "class_subj": 0,
    "marker": 1,
    "order": "SOV",
    "gold": 1,
    "n_subj": "꾍뀙",
    "n_obj": "꾉뀕"
   },
   "answered": true,
   "gold_token": "지"
  },
  {
   "surface": "끱뀁뷔끩뀕퓨달리",
   "swap_target": "끩뀕뷔끱뀁퓨달리",
   "cell": {
    "class_subj": 0,
    "marker": 1,
    "order": "SOV",
    "gold": 1,
    "n_subj": "끱뀁",
    "n_obj": "끩뀕"
   },
   "answered": true,
   "gold_token": "지"
  },
  {
   "surface": "끳뀃뷔꾖뀢퓨달리",
   "swap_target": "꾖뀢뷔끳뀃퓨달리",
   "cell": {
    "class_subj": 0,
    "marker": 1,
    "order": "SOV",
    "gold": 1,
    "n_subj": "끳뀃",
    "n_obj": "꾖뀢"
   },
   "answered": true,
   "gold_token": "지"
  },
  {
   "surface": "끹뀉뷔끹뀥퓨달리",
   "swap_target": "끹뀥뷔끹뀉퓨달리",
   "cell": {
    "class_subj": 0,
    "marker": 1,
    "order": "SOV",
    "gold": 1,
    "n_subj": "끹뀉",
    "n_obj": "끹뀥"
   },
   "answered": true,
   "gold_token": "지"
  },
  {
   "surface": "끶뀆뷔꾓뀟퓨달리",
   "swap_target": "꾓뀟뷔끶뀆퓨달리",
   "cell": {
    "class_subj": 0,
    "marker": 1,
    "order": "SOV",
    "gold": 1,
    "n_subj": "끶뀆",
    "n_obj": "꾓뀟"
   },
   "answered": true,
   "gold_token": "지"
  },
  {
   "surface": "끩꿹뷔끱뀝퓨달리",
   "swap_target": "끱뀝뷔끩꿹퓨달리",
   "cell": {
    "class_subj": 0,
    "marker": 1,
    "order": "SOV",
    "gold": 1,
    "n_subj": "끩꿹",
    "n_obj": "끱뀝"
   },
   "answered": true,
   "gold_token": "지"
  },
  {
   "surface": "꾑뀝뷔꾉뀕퓨달리",
   "swap_target": "꾉뀕뷔꾑뀝퓨달리",
   "cell": {
    "class_subj": 0,
    "marker": 1,
    "order": "SOV",
    "gold": 1,
    "n_subj": "꾑뀝",
    "n_obj": "꾉뀕"
   },
   "answered": true,
   "gold_token": "지"
  },
  {
   "surface": "꾓뀟뷔끶뀢퓨달리",
   "swap_target": "끶뀢뷔꾓뀟퓨달리",
   "cell": {
    "class_subj": 0,
    "marker": 1,
    "order": "SOV",
    "gold": 1,
    "n_subj": "꾓뀟",
    "n_obj": "끶뀢"
   },
   "answered": true,
   "gold_token": "지"
  },
  {
   "surface": "꾖뀢뷔끳뀃퓨달리",
   "swap_target": "끳뀃뷔꾖뀢퓨달리",
   "cell": {
    "class_subj": 0,
    "marker": 1,
    "order": "SOV",
    "gold": 1,
    "n_subj": "꾖뀢",
    "n_obj": "끳뀃"
   },
   "answered": true,
   "gold_token": "지"
  },
  {
   "surface": "꾉뀕뷔꾑뀁퓨달리",
   "swap_target": "꾑뀁뷔꾉뀕퓨달리",
   "cell": {
    "class_subj": 0,
    "marker": 1,
    "order": "SOV",
    "gold": 1,
    "n_subj": "꾉뀕",
    "n_obj": "꾑뀁"
   },
   "answered": true,
   "gold_token": "지"
  },
  {
   "surface": "끱뀁뷔끭꿽퓨달리",
   "swap_target": "끭꿽뷔끱뀁퓨달리",
   "cell": {
    "class_subj": 0,
    "marker": 1,
    "order": "SOV",
    "gold": 1,
    "n_subj": "끱뀁",
    "n_obj": "끭꿽"
   },
   "answered": true,
   "gold_token": "지"
  },
  {
   "surface": "끳뀃뷔꾉꿹퓨달리",
   "swap_target": "꾉꿹뷔끳뀃퓨달리",
   "cell": {
    "class_subj": 0,
    "marker": 1,
    "order": "SOV",
    "gold": 1,
    "n_subj": "끳뀃",
    "n_obj": "꾉꿹"
   },
   "answered": true,
   "gold_token": "지"
  },
  {
   "surface": "끶뀆뷔꾙뀥퓨달리",
   "swap_target": "꾙뀥뷔끶뀆퓨달리",
   "cell": {
    "class_subj": 0,
    "marker": 1,
    "order": "SOV",
    "gold": 1,
    "n_subj": "끶뀆",
    "n_obj": "꾙뀥"
   },
   "answered": true,
   "gold_token": "지"
  },
  {
   "surface": "끶뀢퓨끱뀁뷔달리",
   "swap_target": "끱뀁퓨끶뀢뷔달리",
   "cell": {
    "class_subj": 0,
    "marker": 1,
    "order": "OSV",
    "gold": 1,
    "n_subj": "끱뀁",
    "n_obj": "끶뀢"
   },
   "answered": true,
   "gold_token": "지"
  },
  {
   "surface": "꾙뀥퓨끳뀃뷔달리",
   "swap_target": "끳뀃퓨꾙뀥뷔달리",
   "cell": {
    "class_subj": 0,
    "marker": 1,
    "order": "OSV",
    "gold": 1,
    "n_subj": "끳뀃",
    "n_obj": "꾙뀥"
   },
   "answered": true,
   "gold_token": "지"
  },
  {
   "surface": "끳뀟퓨끹뀉뷔달리",
   "swap_target": "끹뀉퓨끳뀟뷔달리",
   "cell": {
    "class_subj": 0,
    "marker": 1,
    "order": "OSV",
    "gold": 1,
    "n_subj": "끹뀉",
    "n_obj": "끳뀟"
   },
   "answered": true,
   "gold_token": "지"
  },
  {
   "surface": "꾑뀝퓨끶뀆뷔달리",
   "swap_target": "끶뀆퓨꾑뀝뷔달리",
   "cell": {
    "class_subj": 0,
    "marker": 1,
    "order": "OSV",
    "gold": 1,
    "n_subj": "끶뀆",
    "n_obj": "꾑뀝"
   },
   "answered": true,
   "gold_token": "지"
  },
  {
   "surface": "꾍꿽퓨끩꿹뷔달리",
   "swap_target": "끩꿹퓨꾍꿽뷔달리",
   "cell": {
    "class_subj": 0,
    "marker": 1,
    "order": "OSV",
    "gold": 1,
    "n_subj": "끩꿹",
    "n_obj": "꾍꿽"
   },
   "answered": true,
   "gold_token": "지"
  },
  {
   "surface": "끩꿹퓨끭꿽뷔달리",
   "swap_target": "끭꿽퓨끩꿹뷔달리",
   "cell": {
    "class_subj": 0,
    "marker": 1,
    "order": "OSV",
    "gold": 1,
    "n_subj": "끭꿽",
    "n_obj": "끩꿹"
   },
   "answered": true,
   "gold_token": "지"
  },
  {
   "surface": "꾖뀆퓨꾑뀝뷔달리",
   "swap_target": "꾑뀝퓨꾖뀆뷔달리",
   "cell": {
    "class_subj": 0,
    "marker": 1,
    "order": "OSV",
    "gold": 1,
    "n_subj": "꾑뀝",
    "n_obj": "꾖뀆"
   },
   "answered": true,
   "gold_token": "지"
  },
  {
   "surface": "끹뀉퓨꾓뀟뷔달리",
   "swap_target": "꾓뀟퓨끹뀉뷔달리",
   "cell": {
    "class_subj": 0,
    "marker": 1,
    "order": "OSV",
    "gold": 1,
    "n_subj": "꾓뀟",
    "n_obj": "끹뀉"
   },
   "answered": true,
   "gold_token": "지"
  },
  {
   "surface": "꾓뀃퓨꾙뀥뷔달리",
   "swap_target": "꾙뀥퓨꾓뀃뷔달리",
   "cell": {
    "class_subj": 0,
    "marker": 1,
    "order": "OSV",
    "gold": 1,
    "n_subj": "꾙뀥",
    "n_obj": "꾓뀃"
   },
   "answered": true,
   "gold_token": "지"
  },
  {
   "surface": "끱뀁퓨꾖뀢뷔달리",
   "swap_target": "꾖뀢퓨끱뀁뷔달리",
   "cell": {
    "class_subj": 0,
    "marker": 1,
    "order": "OSV",
    "gold": 1,
    "n_subj": "꾖뀢",
    "n_obj": "끱뀁"
   },
   "answered": true,
   "gold_token": "지"
  },
  {
   "surface": "끭뀙퓨꾉뀕뷔달리",
   "swap_target": "꾉뀕퓨끭뀙뷔달리",
   "cell": {
    "class_subj": 0,
    "marker": 1,
    "order": "OSV",
    "gold": 1,
    "n_subj": "꾉뀕",
    "n_obj": "끭뀙"
   },
   "answered": true,
   "gold_token": "지"
  },
  {
   "surface": "꾉뀕퓨꾍뀙뷔달리",
   "swap_target": "꾍뀙퓨꾉뀕뷔달리",
   "cell": {
    "class_subj": 0,
    "marker": 1,
    "order": "OSV",
    "gold": 1,
    "n_subj": "꾍뀙",
    "n_obj": "꾉뀕"
   },
   "answered": true,
   "gold_token": "지"
  },
  {
   "surface": "끩뀕퓨끱뀁뷔달리",
   "swap_target": "끱뀁퓨끩뀕뷔달리",
   "cell": {
    "class_subj": 0,
    "marker": 1,
    "order": "OSV",
    "gold": 1,
    "n_subj": "끱뀁",
    "n_obj": "끩뀕"
   },
   "answered": true,
   "gold_token": "지"
  },
  {
   "surface": "꾖뀢퓨끳뀃뷔달리",
   "swap_target": "끳뀃퓨꾖뀢뷔달리",
   "cell": {
    "class_subj": 0,
    "marker": 1,
    "order": "OSV",
    "gold": 1,
    "n_subj": "끳뀃",
    "n_obj": "꾖뀢"
   },
   "answered": true,
   "gold_token": "지"
  },
  {
   "surface": "끹뀥퓨끹뀉뷔달리",
   "swap_target": "끹뀉퓨끹뀥뷔달리",
   "cell": {
    "class_subj": 0,
    "marker": 1,
    "order": "OSV",
    "gold": 1,
    "n_subj": "끹뀉",
    "n_obj": "끹뀥"
   },
   "answered": true,
   "gold_token": "지"
  },
  {
   "surface": "꾓뀟퓨끶뀆뷔달리",
   "swap_target": "끶뀆퓨꾓뀟뷔달리",
   "cell": {
    "class_subj": 0,
    "marker": 1,
    "order": "OSV",
    "gold": 1,
    "n_subj": "끶뀆",
    "n_obj": "꾓뀟"
   },
   "answered": true,
   "gold_token": "지"
  },
  {
   "surface": "끱뀝퓨끩꿹뷔달리",
   "swap_target": "끩꿹퓨끱뀝뷔달리",
   "cell": {
    "class_subj": 0,
    "marker": 1,
    "order": "OSV",
    "gold": 1,
    "n_subj": "끩꿹",
    "n_obj": "끱뀝"
   },
   "answered": true,
   "gold_token": "지"
  },
  {
   "surface": "꾉뀕퓨꾑뀝뷔달리",
   "swap_target": "꾑뀝퓨꾉뀕뷔달리",
   "cell": {
    "class_subj": 0,
    "marker": 1,
    "order": "OSV",
    "gold": 1,
    "n_subj": "꾑뀝",
    "n_obj": "꾉뀕"
   },
   "answered": true,
   "gold_token": "지"
  },
  {
   "surface": "끶뀢퓨꾓뀟뷔달리",
   "swap_target": "꾓뀟퓨끶뀢뷔달리",
   "cell": {
    "class_subj": 0,
    "marker": 1,
    "order": "OSV",
    "gold": 1,
    "n_subj": "꾓뀟",
    "n_obj": "끶뀢"
   },
   "answered": true,
   "gold_token": "지"
  },
  {
   "surface": "끳뀃퓨꾖뀢뷔달리",
   "swap_target": "꾖뀢퓨끳뀃뷔달리",
   "cell": {
    "class_subj": 0,
    "marker": 1,
    "order": "OSV",
    "gold": 1,
    "n_subj": "꾖뀢",
    "n_obj": "끳뀃"
   },
   "answered": true,
   "gold_token": "지"
  },
  {
   "surface": "꾑뀁퓨꾉뀕뷔달리",
   "swap_target": "꾉뀕퓨꾑뀁뷔달리",
   "cell": {
    "class_subj": 0,
    "marker": 1,
    "order": "OSV",
    "gold": 1,
    "n_subj": "꾉뀕",
    "n_obj": "꾑뀁"
   },
   "answered": true,
   "gold_token": "지"
  },
  {
   "surface": "끭꿽퓨끱뀁뷔달리",
   "swap_target": "끱뀁퓨끭꿽뷔달리",
   "cell": {
    "class_subj": 0,
    "marker": 1,
    "order": "OSV",
    "gold": 1,
    "n_subj": "끱뀁",
    "n_obj": "끭꿽"
   },
   "answered": true,
   "gold_token": "지"
  },
  {
   "surface": "꾉꿹퓨끳뀃뷔달리",
   "swap_target": "끳뀃퓨꾉꿹뷔달리",
   "cell": {
    "class_subj": 0,
    "marker": 1,
    "order": "OSV",
    "gold": 1,
    "n_subj": "끳뀃",
    "n_obj": "꾉꿹"
   },
   "answered": true,
   "gold_token": "지"
  },
  {
   "surface": "꾙뀥퓨끶뀆뷔달리",
   "swap_target": "끶뀆퓨꾙뀥뷔달리",
   "cell": {
    "class_subj": 0,
    "marker": 1,
    "order": "OSV",
    "gold": 1,
    "n_subj": "끶뀆",
    "n_obj": "꾙뀥"
   },
   "answered": true,
   "gold_token": "지"
  },
  {
   "surface": "끱뀝뷔끶뀢죠달리",
   "swap_target": "끶뀢뷔끱뀝죠달리",
   "cell": {
    "class_subj": 1,
    "marker": 0,
    "order": "SOV",
    "gold": 1,
    "n_subj": "끱뀝",
    "n_obj": "끶뀢"
   },
   "answered": true,
   "gold_token": "지"
  },
  {
   "surface": "끳뀟뷔꾙뀥죠달리",
   "swap_target": "꾙뀥뷔끳뀟죠달리",
   "cell": {
    "class_subj": 1,
    "marker": 0,
    "order": "SOV",
    "gold": 1,
    "n_subj": "끳뀟",
    "n_obj": "꾙뀥"
   },
   "answered": true,
   "gold_token": "지"
  },
  {
   "surface": "끹뀥뷔끳뀟죠달리",
   "swap_target": "끳뀟뷔끹뀥죠달리",
   "cell": {
    "class_subj": 1,
    "marker": 0,
    "order": "SOV",
    "gold": 1,
    "n_subj": "끹뀥",
    "n_obj": "끳뀟"
   },
   "answered": true,
   "gold_token": "지"
  },
  {
   "surface": "끶뀢뷔꾑뀝죠달리",
   "swap_target": "꾑뀝뷔끶뀢죠달리",
   "cell": {
    "class_subj": 1,
    "marker": 0,
    "order": "SOV",
    "gold": 1,
    "n_subj": "끶뀢",
    "n_obj": "꾑뀝"
   },
   "answered": true,
   "gold_token": "지"
  },
  {
   "surface": "끩뀕뷔꾍꿽죠달리",
   "swap_target": "꾍꿽뷔끩뀕죠달리",
   "cell": {
    "class_subj": 1,
    "marker": 0,
    "order": "SOV",
    "gold": 1,
    "n_subj": "끩뀕",
    "n_obj": "꾍꿽"
   },
   "answered": true,
   "gold_token": "지"
  },
  {
   "surface": "끭뀙뷔끩꿹죠달리",
   "swap_target": "끩꿹뷔끭뀙죠달리",
   "cell": {
    "class_subj": 1,
    "marker": 0,
    "order": "SOV",
    "gold": 1,
    "n_subj": "끭뀙",
    "n_obj": "끩꿹"
   },
   "answered": true,
   "gold_token": "지"
  },
  {
   "surface": "꾑뀁뷔꾖뀆죠달리",
   "swap_target": "꾖뀆뷔꾑뀁죠달리",
   "cell": {
    "class_subj": 1,
    "marker": 0,
    "order": "SOV",
    "gold": 1,
    "n_subj": "꾑뀁",
    "n_obj": "꾖뀆"
   },
   "answered": true,
   "gold_token": "지"
  },
  {
   "surface": "꾓뀃뷔끹뀉죠달리",
   "swap_target": "끹뀉뷔꾓뀃죠달리",
   "cell": {
    "class_subj": 1,
    "marker": 0,
    "order": "SOV",
    "gold": 1,
    "n_subj": "꾓뀃",
    "n_obj": "끹뀉"
   },
   "answered": true,
   "gold_token": "지"
  },
  {
   "surface": "꾙뀉뷔꾓뀃죠달리",
   "swap_target": "꾓뀃뷔꾙뀉죠달리",
   "cell": {
    "class_subj": 1,
    "marker": 0,
    "order": "SOV",
    "gold": 1,
    "n_subj": "꾙뀉",
    "n_obj": "꾓뀃"
   },
   "answered": true,
   "gold_token": "지"
  },
  {
   "surface": "꾖뀆뷔끱뀁죠달리",
   "swap_target": "끱뀁뷔꾖뀆죠달리",
   "cell": {
    "class_subj": 1,
    "marker": 0,
    "order": "SOV",
    "gold": 1,
    "n_subj": "꾖뀆",
    "n_obj": "끱뀁"
   },
   "answered": true,
   "gold_token": "지"
  },
  {
   "surface": "꾉꿹뷔끭뀙죠달리",
   "swap_target": "끭뀙뷔꾉꿹죠달리",
   "cell": {
    "class_subj": 1,
    "marker": 0,
    "order": "SOV",
    "gold": 1,
    "n_subj": "꾉꿹",
    "n_obj": "끭뀙"
   },
   "answered": true,
   "gold_token": "지"
  },
  {
   "surface": "꾍꿽뷔꾉뀕죠달리",
   "swap_target": "꾉뀕뷔꾍꿽죠달리",
   "cell": {
    "class_subj": 1,
    "marker": 0,
    "order": "SOV",
    "gold": 1,
    "n_subj": "꾍꿽",
    "n_obj": "꾉뀕"
   },
   "answered": true,
   "gold_token": "지"
  },
  {
   "surface": "끱뀝뷔끩뀕죠달리",
   "swap_target": "끩뀕뷔끱뀝죠달리",
   "cell": {
    "class_subj": 1,
    "marker": 0,
    "order": "SOV",
    "gold": 1,
    "n_subj": "끱뀝",
    "n_obj": "끩뀕"
   },
   "answered": true,
   "gold_token": "지"
  },
  {
   "surface": "끳뀟뷔꾖뀢죠달리",
   "swap_target": "꾖뀢뷔끳뀟죠달리",
   "cell": {
    "class_subj": 1,
    "marker": 0,
    "order": "SOV",
    "gold": 1,
    "n_subj": "끳뀟",
    "n_obj": "꾖뀢"
   },
   "answered": true,
   "gold_token": "지"
  },
  {
   "surface": "끶뀢뷔꾓뀃죠달리",
   "swap_target": "꾓뀃뷔끶뀢죠달리",
   "cell": {
    "class_subj": 1,
    "marker": 0,
    "order": "SOV",
    "gold": 1,
    "n_subj": "끶뀢",
    "n_obj": "꾓뀃"
   },
   "answered": true,
   "gold_token": "지"
  },
  {
   "surface": "끩뀕뷔끱뀁죠달리",
   "swap_target": "끱뀁뷔끩뀕죠달리",
   "cell": {
    "class_subj": 1,
    "marker": 0,
    "order": "SOV",
    "gold": 1,
    "n_subj": "끩뀕",
    "n_obj": "끱뀁"
   },
   "answered": true,
   "gold_token": "지"
  },
  {
   "surface": "꾑뀁뷔꾉꿹죠달리",
   "swap_target": "꾉꿹뷔꾑뀁죠달리",
   "cell": {
    "class_subj": 1,
    "marker": 0,
    "order": "SOV",
    "gold": 1,
    "n_subj": "꾑뀁",
    "n_obj": "꾉꿹"
   },
   "answered": true,
   "gold_token": "지"
  },
  {
   "surface": "꾓뀃뷔끶뀆죠달리",
   "swap_target": "끶뀆뷔꾓뀃죠달리",
   "cell": {
    "class_subj": 1,
    "marker": 0,
    "order": "SOV",
    "gold": 1,
    "n_subj": "꾓뀃",
    "n_obj": "끶뀆"
   },
   "answered": true,
   "gold_token": "지"
  },
  {
   "surface": "꾖뀆뷔끳뀟죠달리",
   "swap_target": "끳뀟뷔꾖뀆죠달리",
   "cell": {
    "class_subj": 1,
    "marker": 0,
    "order": "SOV",
    "gold": 1,
    "n_subj": "꾖뀆",
    "n_obj": "끳뀟"
   },
   "answered": true,
   "gold_token": "지"
  },
  {
   "surface": "꾉꿹뷔꾑뀝죠달리",
   "swap_target": "꾑뀝뷔꾉꿹죠달리",
   "cell": {
    "class_subj": 1,
    "marker": 0,
    "order": "SOV",
    "gold": 1,
    "n_subj": "꾉꿹",
    "n_obj": "꾑뀝"
   },
   "answered": true,
   "gold_token": "지"
  },
  {
   "surface": "끱뀝뷔끭뀙죠달리",
   "swap_target": "끭뀙뷔끱뀝죠달리",
   "cell": {
    "class_subj": 1,
    "marker": 0,
    "order": "SOV",
    "gold": 1,
    "n_subj": "끱뀝",
    "n_obj": "끭뀙"
   },
   "answered": true,
   "gold_token": "지"
  },
  {
   "surface": "끳뀟뷔꾉뀕죠달리",
   "swap_target": "꾉뀕뷔끳뀟죠달리",
   "cell": {
    "class_subj": 1,
    "marker": 0,
    "order": "SOV",
    "gold": 1,
    "n_subj": "끳뀟",
    "n_obj": "꾉뀕"
   },
   "answered": true,
   "gold_token": "지"
  },
  {
   "surface": "끶뀢뷔꾙뀉죠달리",
   "swap_target": "꾙뀉뷔끶뀢죠달리",
   "cell": {
    "class_subj": 1,
    "marker": 0,
    "order": "SOV",
    "gold": 1,
    "n_subj": "끶뀢",
    "n_obj": "꾙뀉"
   },
   "answered": true,
   "gold_token": "지"
  },
  {
   "surface": "끩뀕뷔끳뀃죠달리",
   "swap_target": "끳뀃뷔끩뀕죠달리",
   "cell": {
    "class_subj": 1,
    "marker": 0,
    "order": "SOV",
    "gold": 1,
    "n_subj": "끩뀕",
    "n_obj": "끳뀃"
   },
   "answered": true,
   "gold_token": "지"
  },
  {
   "surface": "끶뀢죠끱뀝뷔달리",
   "swap_target": "끱뀝죠끶뀢뷔달리",
   "cell": {
    "class_subj": 1,
    "marker": 0,
    "order": "OSV",
    "gold": 1,
    "n_subj": "끱뀝",
    "n_obj": "끶뀢"
   },
   "answered": true,
   "gold_token": "지"
  },
  {
   "surface": "꾙뀥죠끳뀟뷔달리",
   "swap_target": "끳뀟죠꾙뀥뷔달리",
   "cell": {
    "class_subj": 1,
    "marker": 0,
    "order": "OSV",
    "gold": 1,
    "n_subj": "끳뀟",
    "n_obj": "꾙뀥"
   },
   "answered": true,
   "gold_token": "지"
  },
  {
   "surface": "끳뀟죠끹뀥뷔달리",
   "swap_target": "끹뀥죠끳뀟뷔달리",
   "cell": {
    "class_subj": 1,
    "marker": 0,
    "order": "OSV",
    "gold": 1,
    "n_subj": "끹뀥",
    "n_obj": "끳뀟"
   },
   "answered": true,
   "gold_token": "지"
  },
  {
   "surface": "꾑뀝죠끶뀢뷔달리",
   "swap_target": "끶뀢죠꾑뀝뷔달리",
   "cell": {
    "class_subj": 1,
    "marker": 0,
    "order": "OSV",
    "gold": 1,
    "n_subj": "끶뀢",
    "n_obj": "꾑뀝"
   },
   "answered": true,
   "gold_token": "지"
  },
  {
   "surface": "꾍꿽죠끩뀕뷔달리",
   "swap_target": "끩뀕죠꾍꿽뷔달리",
   "cell": {
    "class_subj": 1,
    "marker": 0,
    "order": "OSV",
    "gold": 1,
    "n_subj": "끩뀕",
    "n_obj": "꾍꿽"
   },
   "answered": true,
   "gold_token": "지"
  },
  {
   "surface": "끩꿹죠끭뀙뷔달리",
   "swap_target": "끭뀙죠끩꿹뷔달리",
   "cell": {
    "class_subj": 1,
    "marker": 0,
    "order": "OSV",
    "gold": 1,
    "n_subj": "끭뀙",
    "n_obj": "끩꿹"
   },
   "answered": true,
   "gold_token": "지"
  },
  {
   "surface": "꾖뀆죠꾑뀁뷔달리",
   "swap_target": "꾑뀁죠꾖뀆뷔달리",
   "cell": {
    "class_subj": 1,
    "marker": 0,
    "order": "OSV",
    "gold": 1,
    "n_subj": "꾑뀁",
    "n_obj": "꾖뀆"
   },
   "answered": true,
   "gold_token": "지"
  },
  {
   "surface": "끹뀉죠꾓뀃뷔달리",
   "swap_target": "꾓뀃죠끹뀉뷔달리",
   "cell": {
    "class_subj": 1,
    "marker": 0,
    "order": "OSV",
    "gold": 1,
    "n_subj": "꾓뀃",
    "n_obj": "끹뀉"
   },
   "answered": true,
   "gold_token": "지"
  },
  {
   "surface": "꾓뀃죠꾙뀉뷔달리",
   "swap_target": "꾙뀉죠꾓뀃뷔달리",
   "cell": {
    "class_subj": 1,
    "marker": 0,
    "order": "OSV",
    "gold": 1,
    "n_subj": "꾙뀉",
    "n_obj": "꾓뀃"
   },
   "answered": true,
   "gold_token": "지"
  },
  {
   "surface": "끱뀁죠꾖뀆뷔달리",
   "swap_target": "꾖뀆죠끱뀁뷔달리",
   "cell": {
    "class_subj": 1,
    "marker": 0,
    "order": "OSV",
    "gold": 1,
    "n_subj": "꾖뀆",
    "n_obj": "끱뀁"
   },
   "answered": true,
   "gold_token": "지"
  },
  {
   "surface": "끭뀙죠꾉꿹뷔달리",
   "swap_target": "꾉꿹죠끭뀙뷔달리",
   "cell": {
    "class_subj": 1,
    "marker": 0,
    "order": "OSV",
    "gold": 1,
    "n_subj": "꾉꿹",
    "n_obj": "끭뀙"
   },
   "answered": true,
   "gold_token": "지"
  },
  {
   "surface": "꾉뀕죠꾍꿽뷔달리",
   "swap_target": "꾍꿽죠꾉뀕뷔달리",
   "cell": {
    "class_subj": 1,
    "marker": 0,
    "order": "OSV",
    "gold": 1,
    "n_subj": "꾍꿽",
    "n_obj": "꾉뀕"
   },
   "answered": true,
   "gold_token": "지"
  },
  {
   "surface": "끩뀕죠끱뀝뷔달리",
   "swap_target": "끱뀝죠끩뀕뷔달리",
   "cell": {
    "class_subj": 1,
    "marker": 0,
    "order": "OSV",
    "gold": 1,
    "n_subj": "끱뀝",
    "n_obj": "끩뀕"
   },
   "answered": true,
   "gold_token": "지"
  },
  {
   "surface": "꾖뀢죠끳뀟뷔달리",
   "swap_target": "끳뀟죠꾖뀢뷔달리",
   "cell": {
    "class_subj": 1,
    "marker": 0,
    "order": "OSV",
    "gold": 1,
    "n_subj": "끳뀟",
    "n_obj": "꾖뀢"
   },
   "answered": true,
   "gold_token": "지"
  },
  {
   "surface": "꾓뀃죠끶뀢뷔달리",
   "swap_target": "끶뀢죠꾓뀃뷔달리",
   "cell": {
    "class_subj": 1,
    "marker": 0,
    "order": "OSV",
    "gold": 1,
    "n_subj": "끶뀢",
    "n_obj": "꾓뀃"
   },
   "answered": true,
   "gold_token": "지"
  },
  {
   "surface": "끱뀁죠끩뀕뷔달리",
   "swap_target": "끩뀕죠끱뀁뷔달리",
   "cell": {
    "class_subj": 1,
    "marker": 0,
    "order": "OSV",
    "gold": 1,
    "n_subj": "끩뀕",
    "n_obj": "끱뀁"
   },
   "answered": true,
   "gold_token": "지"
  },
  {
   "surface": "꾉꿹죠꾑뀁뷔달리",
   "swap_target": "꾑뀁죠꾉꿹뷔달리",
   "cell": {
    "class_subj": 1,
    "marker": 0,
    "order": "OSV",
    "gold": 1,
    "n_subj": "꾑뀁",
    "n_obj": "꾉꿹"
   },
   "answered": true,
   "gold_token": "지"
  },
  {
   "surface": "끶뀆죠꾓뀃뷔달리",
   "swap_target": "꾓뀃죠끶뀆뷔달리",
   "cell": {
    "class_subj": 1,
    "marker": 0,
    "order": "OSV",
    "gold": 1,
    "n_subj": "꾓뀃",
    "n_obj": "끶뀆"
   },
   "answered": true,
   "gold_token": "지"
  },
  {
   "surface": "끳뀟죠꾖뀆뷔달리",
   "swap_target": "꾖뀆죠끳뀟뷔달리",
   "cell": {
    "class_subj": 1,
    "marker": 0,
    "order": "OSV",
    "gold": 1,
    "n_subj": "꾖뀆",
    "n_obj": "끳뀟"
   },
   "answered": true,
   "gold_token": "지"
  },
  {
   "surface": "꾑뀝죠꾉꿹뷔달리",
   "swap_target": "꾉꿹죠꾑뀝뷔달리",
   "cell": {
    "class_subj": 1,
    "marker": 0,
    "order": "OSV",
    "gold": 1,
    "n_subj": "꾉꿹",
    "n_obj": "꾑뀝"
   },
   "answered": true,
   "gold_token": "지"
  },
  {
   "surface": "끭뀙죠끱뀝뷔달리",
   "swap_target": "끱뀝죠끭뀙뷔달리",
   "cell": {
    "class_subj": 1,
    "marker": 0,
    "order": "OSV",
    "gold": 1,
    "n_subj": "끱뀝",
    "n_obj": "끭뀙"
   },
   "answered": true,
   "gold_token": "지"
  },
  {
   "surface": "꾉뀕죠끳뀟뷔달리",
   "swap_target": "끳뀟죠꾉뀕뷔달리",
   "cell": {
    "class_subj": 1,
    "marker": 0,
    "order": "OSV",
    "gold": 1,
    "n_subj": "끳뀟",
    "n_obj": "꾉뀕"
   },
   "answered": true,
   "gold_token": "지"
  },
  {
   "surface": "꾙뀉죠끶뀢뷔달리",
   "swap_target": "끶뀢죠꾙뀉뷔달리",
   "cell": {
    "class_subj": 1,
    "marker": 0,
    "order": "OSV",
    "gold": 1,
    "n_subj": "끶뀢",
    "n_obj": "꾙뀉"
   },
   "answered": true,
   "gold_token": "지"
  },
  {
   "surface": "끳뀃죠끩뀕뷔달리",
   "swap_target": "끩뀕죠끳뀃뷔달리",
   "cell": {
    "class_subj": 1,
    "marker": 0,
    "order": "OSV",
    "gold": 1,
    "n_subj": "끩뀕",
    "n_obj": "끳뀃"
   },
   "answered": true,
   "gold_token": "지"
  },
  {
   "surface": "끱뀝뷔끶뀢퓨달리",
   "swap_target": "끶뀢뷔끱뀝퓨달리",
   "cell": {
    "class_subj": 1,
    "marker": 1,
    "order": "SOV",
    "gold": 0,
    "n_subj": "끱뀝",
    "n_obj": "끶뀢"
   },
   "answered": true,
   "gold_token": "네"
  },
  {
   "surface": "끳뀟뷔꾙뀥퓨달리",
   "swap_target": "꾙뀥뷔끳뀟퓨달리",
   "cell": {
    "class_subj": 1,
    "marker": 1,
    "order": "SOV",
    "gold": 0,
    "n_subj": "끳뀟",
    "n_obj": "꾙뀥"
   },
   "answered": true,
   "gold_token": "네"
  },
  {
   "surface": "끹뀥뷔끳뀟퓨달리",
   "swap_target": "끳뀟뷔끹뀥퓨달리",
   "cell": {
    "class_subj": 1,
    "marker": 1,
    "order": "SOV",
    "gold": 0,
    "n_subj": "끹뀥",
    "n_obj": "끳뀟"
   },
   "answered": true,
   "gold_token": "네"
  },
  {
   "surface": "끶뀢뷔꾑뀝퓨달리",
   "swap_target": "꾑뀝뷔끶뀢퓨달리",
   "cell": {
    "class_subj": 1,
    "marker": 1,
    "order": "SOV",
    "gold": 0,
    "n_subj": "끶뀢",
    "n_obj": "꾑뀝"
   },
   "answered": true,
   "gold_token": "네"
  },
  {
   "surface": "끩뀕뷔꾍꿽퓨달리",
   "swap_target": "꾍꿽뷔끩뀕퓨달리",
   "cell": {
    "class_subj": 1,
    "marker": 1,
    "order": "SOV",
    "gold": 0,
    "n_subj": "끩뀕",
    "n_obj": "꾍꿽"
   },
   "answered": true,
   "gold_token": "네"
  },
  {
   "surface": "끭뀙뷔끩꿹퓨달리",
   "swap_target": "끩꿹뷔끭뀙퓨달리",
   "cell": {
    "class_subj": 1,
    "marker": 1,
    "order": "SOV",
    "gold": 0,
    "n_subj": "끭뀙",
    "n_obj": "끩꿹"
   },
   "answered": true,
   "gold_token": "네"
  },
  {
   "surface": "꾑뀁뷔꾖뀆퓨달리",
   "swap_target": "꾖뀆뷔꾑뀁퓨달리",
   "cell": {
    "class_subj": 1,
    "marker": 1,
    "order": "SOV",
    "gold": 0,
    "n_subj": "꾑뀁",
    "n_obj": "꾖뀆"
   },
   "answered": true,
   "gold_token": "네"
  },
  {
   "surface": "꾓뀃뷔끹뀉퓨달리",
   "swap_target": "끹뀉뷔꾓뀃퓨달리",
   "cell": {
    "class_subj": 1,
    "marker": 1,
    "order": "SOV",
    "gold": 0,
    "n_subj": "꾓뀃",
    "n_obj": "끹뀉"
   },
   "answered": true,
   "gold_token": "네"
  },
  {
   "surface": "꾙뀉뷔꾓뀃퓨달리",
   "swap_target": "꾓뀃뷔꾙뀉퓨달리",
   "cell": {
    "class_subj": 1,
    "marker": 1,
    "order": "SOV",
    "gold": 0,
    "n_subj": "꾙뀉",
    "n_obj": "꾓뀃"
   },
   "answered": true,
   "gold_token": "네"
  },
  {
   "surface": "꾖뀆뷔끱뀁퓨달리",
   "swap_target": "끱뀁뷔꾖뀆퓨달리",
   "cell": {
    "class_subj": 1,
    "marker": 1,
    "order": "SOV",
    "gold": 0,
    "n_subj": "꾖뀆",
    "n_obj": "끱뀁"
   },
   "answered": true,
   "gold_token": "네"
  },
  {
   "surface": "꾉꿹뷔끭뀙퓨달리",
   "swap_target": "끭뀙뷔꾉꿹퓨달리",
   "cell": {
    "class_subj": 1,
    "marker": 1,
    "order": "SOV",
    "gold": 0,
    "n_subj": "꾉꿹",
    "n_obj": "끭뀙"
   },
   "answered": true,
   "gold_token": "네"
  },
  {
   "surface": "꾍꿽뷔꾉뀕퓨달리",
   "swap_target": "꾉뀕뷔꾍꿽퓨달리",
   "cell": {
    "class_subj": 1,
    "marker": 1,
    "order": "SOV",
    "gold": 0,
    "n_subj": "꾍꿽",
    "n_obj": "꾉뀕"
   },
   "answered": true,
   "gold_token": "네"
  },
  {
   "surface": "끱뀝뷔끩뀕퓨달리",
   "swap_target": "끩뀕뷔끱뀝퓨달리",
   "cell": {
    "class_subj": 1,
    "marker": 1,
    "order": "SOV",
    "gold": 0,
    "n_subj": "끱뀝",
    "n_obj": "끩뀕"
   },
   "answered": true,
   "gold_token": "네"
  },
  {
   "surface": "끳뀟뷔꾖뀢퓨달리",
   "swap_target": "꾖뀢뷔끳뀟퓨달리",
   "cell": {
    "class_subj": 1,
    "marker": 1,
    "order": "SOV",
    "gold": 0,
    "n_subj": "끳뀟",
    "n_obj": "꾖뀢"
   },
   "answered": true,
   "gold_token": "네"
  },
  {
   "surface": "끶뀢뷔꾓뀃퓨달리",
   "swap_target": "꾓뀃뷔끶뀢퓨달리",
   "cell": {
    "class_subj": 1,
    "marker": 1,
    "order": "SOV",
    "gold": 0,
    "n_subj": "끶뀢",
    "n_obj": "꾓뀃"
   },
   "answered": true,
   "gold_token": "네"
  },
  {
   "surface": "끩뀕뷔끱뀁퓨달리",
   "swap_target": "끱뀁뷔끩뀕퓨달리",
   "cell": {
    "class_subj": 1,
    "marker": 1,
    "order": "SOV",
    "gold": 0,
    "n_subj": "끩뀕",
    "n_obj": "끱뀁"
   },
   "answered": true,
   "gold_token": "네"
  },
  {
   "surface": "꾑뀁뷔꾉꿹퓨달리",
   "swap_target": "꾉꿹뷔꾑뀁퓨달리",
   "cell": {
    "class_subj": 1,
    "marker": 1,
    "order": "SOV",
    "gold": 0,
    "n_subj": "꾑뀁",
    "n_obj": "꾉꿹"
   },
   "answered": true,
   "gold_token": "네"
  },
  {
   "surface": "꾓뀃뷔끶뀆퓨달리",
   "swap_target": "끶뀆뷔꾓뀃퓨달리",
   "cell": {
    "class_subj": 1,
    "marker": 1,
    "order": "SOV",
    "gold": 0,
    "n_subj": "꾓뀃",
    "n_obj": "끶뀆"
   },
   "answered": true,
   "gold_token": "네"
  },
  {
   "surface": "꾖뀆뷔끳뀟퓨달리",
   "swap_target": "끳뀟뷔꾖뀆퓨달리",
   "cell": {
    "class_subj": 1,
    "marker": 1,
    "order": "SOV",
    "gold": 0,
    "n_subj": "꾖뀆",
    "n_obj": "끳뀟"
   },
   "answered": true,
   "gold_token": "네"
  },
  {
   "surface": "꾉꿹뷔꾑뀝퓨달리",
   "swap_target": "꾑뀝뷔꾉꿹퓨달리",
   "cell": {
    "class_subj": 1,
    "marker": 1,
    "order": "SOV",
    "gold": 0,
    "n_subj": "꾉꿹",
    "n_obj": "꾑뀝"
   },
   "answered": true,
   "gold_token": "네"
  },
  {
   "surface": "끱뀝뷔끭뀙퓨달리",
   "swap_target": "끭뀙뷔끱뀝퓨달리",
   "cell": {
    "class_subj": 1,
    "marker": 1,
    "order": "SOV",
    "gold": 0,
    "n_subj": "끱뀝",
    "n_obj": "끭뀙"
   },
   "answered": true,
   "gold_token": "네"
  },
  {
   "surface": "끳뀟뷔꾉뀕퓨달리",
   "swap_target": "꾉뀕뷔끳뀟퓨달리",
   "cell": {
    "class_subj": 1,
    "marker": 1,
    "order": "SOV",
    "gold": 0,
    "n_subj": "끳뀟",
    "n_obj": "꾉뀕"
   },
   "answered": true,
   "gold_token": "네"
  },
  {
   "surface": "끶뀢뷔꾙뀉퓨달리",
   "swap_target": "꾙뀉뷔끶뀢퓨달리",
   "cell": {
    "class_subj": 1,
    "marker": 1,
    "order": "SOV",
    "gold": 0,
    "n_subj": "끶뀢",
    "n_obj": "꾙뀉"
   },
   "answered": true,
   "gold_token": "네"
  },
  {
   "surface": "끩뀕뷔끳뀃퓨달리",
   "swap_target": "끳뀃뷔끩뀕퓨달리",
   "cell": {
    "class_subj": 1,
    "marker": 1,
    "order": "SOV",
    "gold": 0,
    "n_subj": "끩뀕",
    "n_obj": "끳뀃"
   },
   "answered": true,
   "gold_token": "네"
  },
  {
   "surface": "끶뀢퓨끱뀝뷔달리",
   "swap_target": "끱뀝퓨끶뀢뷔달리",
   "cell": {
    "class_subj": 1,
    "marker": 1,
    "order": "OSV",
    "gold": 0,
    "n_subj": "끱뀝",
    "n_obj": "끶뀢"
   },
   "answered": true,
   "gold_token": "네"
  },
  {
   "surface": "꾙뀥퓨끳뀟뷔달리",
   "swap_target": "끳뀟퓨꾙뀥뷔달리",
   "cell": {
    "class_subj": 1,
    "marker": 1,
    "order": "OSV",
    "gold": 0,
    "n_subj": "끳뀟",
    "n_obj": "꾙뀥"
   },
   "answered": true,
   "gold_token": "네"
  },
  {
   "surface": "끳뀟퓨끹뀥뷔달리",
   "swap_target": "끹뀥퓨끳뀟뷔달리",
   "cell": {
    "class_subj": 1,
    "marker": 1,
    "order": "OSV",
    "gold": 0,
    "n_subj": "끹뀥",
    "n_obj": "끳뀟"
   },
   "answered": true,
   "gold_token": "네"
  },
  {
   "surface": "꾑뀝퓨끶뀢뷔달리",
   "swap_target": "끶뀢퓨꾑뀝뷔달리",
   "cell": {
    "class_subj": 1,
    "marker": 1,
    "order": "OSV",
    "gold": 0,
    "n_subj": "끶뀢",
    "n_obj": "꾑뀝"
   },
   "answered": true,
   "gold_token": "네"
  },
  {
   "surface": "꾍꿽퓨끩뀕뷔달리",
   "swap_target": "끩뀕퓨꾍꿽뷔달리",
   "cell": {
    "class_subj": 1,
    "marker": 1,
    "order": "OSV",
    "gold": 0,
    "n_subj": "끩뀕",
    "n_obj": "꾍꿽"
   },
   "answered": true,
   "gold_token": "네"
  },
  {
   "surface": "끩꿹퓨끭뀙뷔달리",
   "swap_target": "끭뀙퓨끩꿹뷔달리",
   "cell": {
    "class_subj": 1,
    "marker": 1,
    "order": "OSV",
    "gold": 0,
    "n_subj": "끭뀙",
    "n_obj": "끩꿹"
   },
   "answered": true,
   "gold_token": "네"
  },
  {
   "surface": "꾖뀆퓨꾑뀁뷔달리",
   "swap_target": "꾑뀁퓨꾖뀆뷔달리",
   "cell": {
    "class_subj": 1,
    "marker": 1,
    "order": "OSV",
    "gold": 0,
    "n_subj": "꾑뀁",
    "n_obj": "꾖뀆"
   },
   "answered": true,
   "gold_token": "네"
  },
  {
   "surface": "끹뀉퓨꾓뀃뷔달리",
   "swap_target": "꾓뀃퓨끹뀉뷔달리",
   "cell": {
    "class_subj": 1,
    "marker": 1,
    "order": "OSV",
    "gold": 0,
    "n_subj": "꾓뀃",
    "n_obj": "끹뀉"
   },
   "answered": true,
   "gold_token": "네"
  },
  {
   "surface": "꾓뀃퓨꾙뀉뷔달리",
   "swap_target": "꾙뀉퓨꾓뀃뷔달리",
   "cell": {
    "class_subj": 1,
    "marker": 1,
    "order": "OSV",
    "gold": 0,
    "n_subj": "꾙뀉",
    "n_obj": "꾓뀃"
   },
   "answered": true,
   "gold_token": "네"
  },
  {
   "surface": "끱뀁퓨꾖뀆뷔달리",
   "swap_target": "꾖뀆퓨끱뀁뷔달리",
   "cell": {
    "class_subj": 1,
    "marker": 1,
    "order": "OSV",
    "gold": 0,
    "n_subj": "꾖뀆",
    "n_obj": "끱뀁"
   },
   "answered": true,
   "gold_token": "네"
  },
  {
   "surface": "끭뀙퓨꾉꿹뷔달리",
   "swap_target": "꾉꿹퓨끭뀙뷔달리",
   "cell": {
    "class_subj": 1,
    "marker": 1,
    "order": "OSV",
    "gold": 0,
    "n_subj": "꾉꿹",
    "n_obj": "끭뀙"
   },
   "answered": true,
   "gold_token": "네"
  },
  {
   "surface": "꾉뀕퓨꾍꿽뷔달리",
   "swap_target": "꾍꿽퓨꾉뀕뷔달리",
   "cell": {
    "class_subj": 1,
    "marker": 1,
    "order": "OSV",
    "gold": 0,
    "n_subj": "꾍꿽",
    "n_obj": "꾉뀕"
   },
   "answered": true,
   "gold_token": "네"
  },
  {
   "surface": "끩뀕퓨끱뀝뷔달리",
   "swap_target": "끱뀝퓨끩뀕뷔달리",
   "cell": {
    "class_subj": 1,
    "marker": 1,
    "order": "OSV",
    "gold": 0,
    "n_subj": "끱뀝",
    "n_obj": "끩뀕"
   },
   "answered": true,
   "gold_token": "네"
  },
  {
   "surface": "꾖뀢퓨끳뀟뷔달리",
   "swap_target": "끳뀟퓨꾖뀢뷔달리",
   "cell": {
    "class_subj": 1,
    "marker": 1,
    "order": "OSV",
    "gold": 0,
    "n_subj": "끳뀟",
    "n_obj": "꾖뀢"
   },
   "answered": true,
   "gold_token": "네"
  },
  {
   "surface": "꾓뀃퓨끶뀢뷔달리",
   "swap_target": "끶뀢퓨꾓뀃뷔달리",
   "cell": {
    "class_subj": 1,
    "marker": 1,
    "order": "OSV",
    "gold": 0,
    "n_subj": "끶뀢",
    "n_obj": "꾓뀃"
   },
   "answered": true,
   "gold_token": "네"
  },
  {
   "surface": "끱뀁퓨끩뀕뷔달리",
   "swap_target": "끩뀕퓨끱뀁뷔달리",
   "cell": {
    "class_subj": 1,
    "marker": 1,
    "order": "OSV",
    "gold": 0,
    "n_subj": "끩뀕",
    "n_obj": "끱뀁"
   },
   "answered": true,
   "gold_token": "네"
  },
  {
   "surface": "꾉꿹퓨꾑뀁뷔달리",
   "swap_target": "꾑뀁퓨꾉꿹뷔달리",
   "cell": {
    "class_subj": 1,
    "marker": 1,
    "order": "OSV",
    "gold": 0,
    "n_subj": "꾑뀁",
    "n_obj": "꾉꿹"
   },
   "answered": true,
   "gold_token": "네"
  },
  {
   "surface": "끶뀆퓨꾓뀃뷔달리",
   "swap_target": "꾓뀃퓨끶뀆뷔달리",
   "cell": {
    "class_subj": 1,
    "marker": 1,
    "order": "OSV",
    "gold": 0,
    "n_subj": "꾓뀃",
    "n_obj": "끶뀆"
   },
   "answered": true,
   "gold_token": "네"
  },
  {
   "surface": "끳뀟퓨꾖뀆뷔달리",
   "swap_target": "꾖뀆퓨끳뀟뷔달리",
   "cell": {
    "class_subj": 1,
    "marker": 1,
    "order": "OSV",
    "gold": 0,
    "n_subj": "꾖뀆",
    "n_obj": "끳뀟"
   },
   "answered": true,
   "gold_token": "네"
  },
  {
   "surface": "꾑뀝퓨꾉꿹뷔달리",
   "swap_target": "꾉꿹퓨꾑뀝뷔달리",
   "cell": {
    "class_subj": 1,
    "marker": 1,
    "order": "OSV",
    "gold": 0,
    "n_subj": "꾉꿹",
    "n_obj": "꾑뀝"
   },
   "answered": true,
   "gold_token": "네"
  },
  {
   "surface": "끭뀙퓨끱뀝뷔달리",
   "swap_target": "끱뀝퓨끭뀙뷔달리",
   "cell": {
    "class_subj": 1,
    "marker": 1,
    "order": "OSV",
    "gold": 0,
    "n_subj": "끱뀝",
    "n_obj": "끭뀙"
   },
   "answered": true,
   "gold_token": "네"
  },
  {
   "surface": "꾉뀕퓨끳뀟뷔달리",
   "swap_target": "끳뀟퓨꾉뀕뷔달리",
   "cell": {
    "class_subj": 1,
    "marker": 1,
    "order": "OSV",
    "gold": 0,
    "n_subj": "끳뀟",
    "n_obj": "꾉뀕"
   },
   "answered": true,
   "gold_token": "네"
  },
  {
   "surface": "꾙뀉퓨끶뀢뷔달리",
   "swap_target": "끶뀢퓨꾙뀉뷔달리",
   "cell": {
    "class_subj": 1,
    "marker": 1,
    "order": "OSV",
    "gold": 0,
    "n_subj": "끶뀢",
    "n_obj": "꾙뀉"
   },
   "answered": true,
   "gold_token": "네"
  },
  {
   "surface": "끳뀃퓨끩뀕뷔달리",
   "swap_target": "끩뀕퓨끳뀃뷔달리",
   "cell": {
    "class_subj": 1,
    "marker": 1,
    "order": "OSV",
    "gold": 0,
    "n_subj": "끩뀕",
    "n_obj": "끳뀃"
   },
   "answered": true,
   "gold_token": "네"
  }
 ],
 "meta": {
  "gold_rule": "class(subject) XOR form(object-marker)",
  "answer_forms": [
   "네",
   "지"
  ],
  "budget_hashes": {
   "24": "1879bcc26fde",
   "96": "f40cf25f594c",
   "192": "38b83da81eee",
   "384": "f4484c43a906"
  },
  "kind": "f2_verdict_ood",
  "n": 192
 }
}